logdensity/__init__.py
logdensity/__main__.py
logdensity/arguments.py
logdensity/runner.py
logdensity-0.1.dev0.dist-info/COPYING
logdensity-0.1.dev0.dist-info/LICENSE
logdensity-0.1.dev0.dist-info/METADATA
logdensity-0.1.dev0.dist-info/WHEEL
logdensity-0.1.dev0.dist-info/entry_points.txt
logdensity-0.1.dev0.dist-info/top_level.txt
logdensity-0.1.dev0.dist-info/RECORD
